Metadata-Version: 2.1
Name: simpledataset
Version: 0.2.2
Summary: Utility tools for SIMPLE vision dataset format.
Home-page: https://github.com/shonohs/simpledataset
License: MIT
Platform: UNKNOWN
Classifier: Intended Audience :: Developers
Classifier: License :: OSI Approved :: MIT License
Requires-Dist: pillow
Requires-Dist: requests
Requires-Dist: scipy
Requires-Dist: tenacity
Requires-Dist: tqdm
